modeltranslation/__init__.py
modeltranslation/_compat.py
modeltranslation/_typing.py
modeltranslation/admin.py
modeltranslation/apps.py
modeltranslation/decorators.py
modeltranslation/fields.py
modeltranslation/forms.py
modeltranslation/manager.py
modeltranslation/models.py
modeltranslation/py.typed
modeltranslation/settings.py
modeltranslation/thread_context.py
modeltranslation/translator.py
modeltranslation/utils.py
modeltranslation/widgets.py
modeltranslation/management/__init__.py
modeltranslation/management/commands/__init__.py
modeltranslation/management/commands/loaddata.py
modeltranslation/management/commands/sync_translation_fields.py
modeltranslation/management/commands/update_translation_fields.py
modeltranslation/static/modeltranslation/css/tabbed_translation_fields.css
modeltranslation/static/modeltranslation/js/clearable_inputs.js
modeltranslation/static/modeltranslation/js/force_jquery.js
modeltranslation/static/modeltranslation/js/tabbed_translation_fields.js
django_modeltranslation-0.19.11.dist-info/AUTHORS.rst
django_modeltranslation-0.19.11.dist-info/LICENSE.txt
django_modeltranslation-0.19.11.dist-info/METADATA
django_modeltranslation-0.19.11.dist-info/WHEEL
django_modeltranslation-0.19.11.dist-info/top_level.txt
django_modeltranslation-0.19.11.dist-info/RECORD
