Metadata-Version: 2.1
Name: django-modeltranslation
Version: 0.19.11
Summary: Translates Django models using a registration approach.
Home-page: https://github.com/deschler/django-modeltranslation
Author: Peter Eschler
Author-email: peschler@gmail.com
Maintainer: Sergiy Tereshchenko
Maintainer-email: serg.partizan+modeltranslation@gmail.com
License: New BSD
Project-URL: Source, https://github.com/deschler/django-modeltranslation
Project-URL: Documentation, https://django-modeltranslation.readthedocs.org/en/latest
Project-URL: Mailing List, http://groups.google.com/group/django-modeltranslation
Project-URL: Changelog, https://github.com/deschler/django-modeltranslation/blob/master/CHANGELOG.md
Classifier: Programming Language :: Python
Classifier: Programming Language :: Python :: 3.9
Classifier: Programming Language :: Python :: 3.10
Classifier: Programming Language :: Python :: 3.11
Classifier: Programming Language :: Python :: 3.12
Classifier: Operating System :: OS Independent
Classifier: Environment :: Web Environment
Classifier: Intended Audience :: Developers
Classifier: Framework :: Django
Classifier: License :: OSI Approved :: BSD License
License-File: LICENSE.txt
License-File: AUTHORS.rst
Requires-Dist: Django>=4.2
Requires-Dist: typing-extensions>=4.0.1; python_version < "3.11"
